AUTHORS
LICENSE
MANIFEST.in
README.rst
setup.py
src/serafin_sqlalchemy/__init__.py
src/serafin_sqlalchemy.egg-info/PKG-INFO
src/serafin_sqlalchemy.egg-info/SOURCES.txt
src/serafin_sqlalchemy.egg-info/dependency_links.txt
src/serafin_sqlalchemy.egg-info/requires.txt
src/serafin_sqlalchemy.egg-info/top_level.txt