Metadata-Version: 1.1
Name: serafin-sqlalchemy
Version: 0.0
Summary: SQLAlchemy integration for serafin
Home-page: http://github.com/novopl/serafin-sqlalchemy
Author: Mateusz 'novo' Klos
Author-email: novopl@gmail.com
License: MIT
Keywords: serafin serialize sql sqlalchemy serialization json config
Platform: UNKNOWN
Classifier: Development Status :: 4 - Beta
Classifier: Topic :: Utilities
Classifier: Intended Audience :: Developers
Classifier: Programming Language :: Python
Classifier: License :: OSI Approved :: MIT License
